genwal/__init__.py
genwal/__main__.py
genwal-0.0.1.dist-info/LICENSE
genwal-0.0.1.dist-info/METADATA
genwal-0.0.1.dist-info/WHEEL
genwal-0.0.1.dist-info/top_level.txt
genwal-0.0.1.dist-info/RECORD
