Metadata-Version: 2.1
Name: genwal
Version: 0.0.1
Summary: Little python script to generate Gentoo wallpapers
Home-page: https://github.com/GrbavaCigla/genwal
Author: Aleksa Ognjanovic
Author-email: alexa.ognjanovic@gmail.com
License: UNKNOWN
Platform: UNKNOWN
Classifier: Programming Language :: Python :: 3
Classifier: Operating System :: POSIX :: Linux
Requires-Python: >=3.4
